mechanismaf/__init__.py
mechanismaf/components.py
mechanismaf/mechanismaf.py
mechanismaf-0.1.2.dist-info/LICENSE
mechanismaf-0.1.2.dist-info/METADATA
mechanismaf-0.1.2.dist-info/WHEEL
mechanismaf-0.1.2.dist-info/top_level.txt
mechanismaf-0.1.2.dist-info/RECORD
